<?xml version='1.0' encoding='UTF-8'?><avatars><avatar id='-1' type='0' levels='3' file='contact.png'><avatar id='-2' type='0' levels='3' file='channel.png'><avatar id='-3' type='0' levels='3' file='notice.png'><avatar id='-4' type='0' levels='2' file='message1.png'><avatar id='-5' type='0' levels='2' file='message2.png'><avatar id='-6' type='0' levels='3' file='place.png'><avatar id='-7' type='0' levels='2' file='positioning1.png'><avatar id='-8' type='1' levels='2' file='positioning2.png'><avatar id='-9' type='1' levels='3' file='link.png'><avatar id='-32' type='1' levels='2' file='typing.png'><avatar id='-33' type='1' levels='3' file='locked.png'><avatar id='-34' type='1' levels='3' file='directory.png'><avatar id='-35' type='1' levels='2' file='message3.png'></avatars></?xml?>